GlideKV/__init__.py
GlideKV/_lookup_ops.so
GlideKV/glidekv.py
glidekv-4.6.9.3.dist-info/licenses/LICENSE
glidekv-4.6.9.3.dist-info/METADATA
glidekv-4.6.9.3.dist-info/WHEEL
glidekv-4.6.9.3.dist-info/top_level.txt
glidekv-4.6.9.3.dist-info/RECORD
